Workbook

Sheet Supermart_Grocery_Sales_Dashboa
A1: Order ID | B1: Customer Name | C1: Category | D1: Sub Category | E1: City | F1: Order Date | G1: Region | H1: Sales | I1: Discount | J1: Profit | K1: State | L1: Clean_Order_Date | M1: Order_Year | N1: Order_Month | O1: Year_Month
A2: OD1 | B2: Harish | C2: Oil & Masala | D2: Masalas | E2: Vellore | F2: 42958 | G2: North | H2: 1254 | I2: 0.12 | J2: 401.28 | K2: Tamil Nadu | L2: =IF(ISNUMBER(F2),F2,IFERROR(DATE(VALUE(RIGHT(F2,4)),VALUE(LEFT(F2,FIND("/",F2)-1)),VALUE(MID(F2,FIND("/",F2)+1,FIND("/",F2,FIND("/",F2)+1)-FIND("/",F2)-1))),"")) -> 42958 | M2: =YEAR(L2) -> 2017 | N2: =MONTH(L2) -> 8 | O2: =TEXT(L2,"yyyy-mm") -> 2017-08
A3: OD2 | B3: Sudha | C3: Beverages | D3: Health Drinks | E3: Krishnagiri | F3: 42958 | G3: South | H3: 749 | I3: 0.18 | J3: 149.8 | K3: Tamil Nadu | L3: =IF(ISNUMBER(F3),F3,IFERROR(DATE(VALUE(RIGHT(F3,4)),VALUE(LEFT(F3,FIND("/",F3)-1)),VALUE(MID(F3,FIND("/",F3)+1,FIND("/",F3,FIND("/",F3)+1)-FIND("/",F3)-1))),"")) -> 42958 | M3: =YEAR(L3) -> 2017 | N3: =MONTH(L3) -> 8 | O3: =TEXT(L3,"yyyy-mm") -> 2017-08
A4: OD3 | B4: Hussain | C4: Food Grains | D4: Atta & Flour | E4: Perambalur | F4: 43075 | G4: West | H4: 2360 | I4: 0.21 | J4: 165.2 | K4: Tamil Nadu | L4: =IF(ISNUMBER(F4),F4,IFERROR(DATE(VALUE(RIGHT(F4,4)),VALUE(LEFT(F4,FIND("/",F4)-1)),VALUE(MID(F4,FIND("/",F4)+1,FIND("/",F4,FIND("/",F4)+1)-FIND("/",F4)-1))),"")) -> 43075 | M4: =YEAR(L4) -> 2017 | N4: =MONTH(L4) -> 12 | O4: =TEXT(L4,"yyyy-mm") -> 2017-12
A5: OD4 | B5: Jackson | C5: Fruits & Veggies | D5: Fresh Vegetables | E5: Dharmapuri | F5: 42684 | G5: South | H5: 896 | I5: 0.25 | J5: 89.6 | K5: Tamil Nadu | L5: =IF(ISNUMBER(F5),F5,IFERROR(DATE(VALUE(RIGHT(F5,4)),VALUE(LEFT(F5,FIND("/",F5)-1)),VALUE(MID(F5,FIND("/",F5)+1,FIND("/",F5,FIND("/",F5)+1)-FIND("/",F5)-1))),"")) -> 42684 | M5: =YEAR(L5) -> 2016 | N5: =MONTH(L5) -> 11 | O5: =TEXT(L5,"yyyy-mm") -> 2016-11
A6: OD5 | B6: Ridhesh | C6: Food Grains | D6: Organic Staples | E6: Ooty | F6: 42684 | G6: South | H6: 2355 | I6: 0.26 | J6: 918.45 | K6: Tamil Nadu | L6: =IF(ISNUMBER(F6),F6,IFERROR(DATE(VALUE(RIGHT(F6,4)),VALUE(LEFT(F6,FIND("/",F6)-1)),VALUE(MID(F6,FIND("/",F6)+1,FIND("/",F6,FIND("/",F6)+1)-FIND("/",F6)-1))),"")) -> 42684 | M6: =YEAR(L6) -> 2016 | N6: =MONTH(L6) -> 11 | O6: =TEXT(L6,"yyyy-mm") -> 2016-11
A7: OD6 | B7: Adavan | C7: Food Grains | D7: Organic Staples | E7: Dharmapuri | F7: 42253 | G7: West | H7: 2305 | I7: 0.26 | J7: 322.7 | K7: Tamil Nadu | L7: =IF(ISNUMBER(F7),F7,IFERROR(DATE(VALUE(RIGHT(F7,4)),VALUE(LEFT(F7,FIND("/",F7)-1)),VALUE(MID(F7,FIND("/",F7)+1,FIND("/",F7,FIND("/",F7)+1)-FIND("/",F7)-1))),"")) -> 42253 | M7: =YEAR(L7) -> 2015 | N7: =MONTH(L7) -> 9 | O7: =TEXT(L7,"yyyy-mm") -> 2015-09
A8: OD7 | B8: Jonas | C8: Fruits & Veggies | D8: Fresh Vegetables | E8: Trichy | F8: 42253 | G8: West | H8: 826 | I8: 0.33 | J8: 346.92 | K8: Tamil Nadu | L8: =IF(ISNUMBER(F8),F8,IFERROR(DATE(VALUE(RIGHT(F8,4)),VALUE(LEFT(F8,FIND("/",F8)-1)),VALUE(MID(F8,FIND("/",F8)+1,FIND("/",F8,FIND("/",F8)+1)-FIND("/",F8)-1))),"")) -> 42253 | M8: =YEAR(L8) -> 2015 | N8: =MONTH(L8) -> 9 | O8: =TEXT(L8,"yyyy-mm") -> 2015-09
A9: OD8 | B9: Hafiz | C9: Fruits & Veggies | D9: Fresh Fruits | E9: Ramanadhapuram | F9: 42253 | G9: West | H9: 1847 | I9: 0.32 | J9: 147.76 | K9: Tamil Nadu | L9: =IF(ISNUMBER(F9),F9,IFERROR(DATE(VALUE(RIGHT(F9,4)),VALUE(LEFT(F9,FIND("/",F9)-1)),VALUE(MID(F9,FIND("/",F9)+1,FIND("/",F9,FIND("/",F9)+1)-FIND("/",F9)-1))),"")) -> 42253 | M9: =YEAR(L9) -> 2015 | N9: =MONTH(L9) -> 9 | O9: =TEXT(L9,"yyyy-mm") -> 2015-09
A10: OD9 | B10: Hafiz | C10: Bakery | D10: Biscuits | E10: Tirunelveli | F10: 42253 | G10: West | H10: 791 | I10: 0.23 | J10: 181.93 | K10: Tamil Nadu | L10: =IF(ISNUMBER(F10),F10,IFERROR(DATE(VALUE(RIGHT(F10,4)),VALUE(LEFT(F10,FIND("/",F10)-1)),VALUE(MID(F10,FIND("/",F10)+1,FIND("/",F10,FIND("/",F10)+1)-FIND("/",F10)-1))),"")) -> 42253 | M10: =YEAR(L10) -> 2015 | N10: =MONTH(L10) -> 9 | O10: =TEXT(L10,"yyyy-mm") -> 2015-09
A11: OD10 | B11: Krithika | C11: Bakery | D11: Cakes | E11: Chennai | F11: 42253 | G11: West | H11: 1795 | I11: 0.27 | J11: 484.65 | K11: Tamil Nadu | L11: =IF(ISNUMBER(F11),F11,IFERROR(DATE(VALUE(RIGHT(F11,4)),VALUE(LEFT(F11,FIND("/",F11)-1)),VALUE(MID(F11,FIND("/",F11)+1,FIND("/",F11,FIND("/",F11)+1)-FIND("/",F11)-1))),"")) -> 42253 | M11: =YEAR(L11) -> 2015 | N11: =MONTH(L11) -> 9 | O11: =TEXT(L11,"yyyy-mm") -> 2015-09
A12: OD11 | B12: Ganesh | C12: Snacks | D12: Chocolates | E12: Karur | F12: 42253 | G12: West | H12: 1903 | I12: 0.13 | J12: 437.69 | K12: Tamil Nadu | L12: =IF(ISNUMBER(F12),F12,IFERROR(DATE(VALUE(RIGHT(F12,4)),VALUE(LEFT(F12,FIND("/",F12)-1)),VALUE(MID(F12,FIND("/",F12)+1,FIND("/",F12,FIND("/",F12)+1)-FIND("/",F12)-1))),"")) -> 42253 | M12: =YEAR(L12) -> 2015 | N12: =MONTH(L12) -> 9 | O12: =TEXT(L12,"yyyy-mm") -> 2015-09
A13: OD12 | B13: Yadav | C13: Eggs, Meat & Fish | D13: Eggs | E13: Namakkal | F13: 42253 | G13: West | H13: 701 | I13: 0.1 | J13: 308.44 | K13: Tamil Nadu | L13: =IF(ISNUMBER(F13),F13,IFERROR(DATE(VALUE(RIGHT(F13,4)),VALUE(LEFT(F13,FIND("/",F13)-1)),VALUE(MID(F13,FIND("/",F13)+1,FIND("/",F13,FIND("/",F13)+1)-FIND("/",F13)-1))),"")) -> 42253 | M13: =YEAR(L13) -> 2015 | N13: =MONTH(L13) -> 9 | O13: =TEXT(L13,"yyyy-mm") -> 2015-09
A14: OD13 | B14: Sharon | C14: Snacks | D14: Cookies | E14: Dindigul | F14: 4/15/2018 | G14: South | H14: 1659 | I14: 0.19 | J14: 315.21 | K14: Tamil Nadu | L14: =IF(ISNUMBER(F14),F14,IFERROR(DATE(VALUE(RIGHT(F14,4)),VALUE(LEFT(F14,FIND("/",F14)-1)),VALUE(MID(F14,FIND("/",F14)+1,FIND("/",F14,FIND("/",F14)+1)-FIND("/",F14)-1))),"")) -> 43205 | M14: =YEAR(L14) -> 2018 | N14: =MONTH(L14) -> 4 | O14: =TEXT(L14,"yyyy-mm") -> 2018-04
A15: OD14 | B15: Peer | C15: Fruits & Veggies | D15: Fresh Vegetables | E15: Kanyakumari | F15: 42867 | G15: West | H15: 1277 | I15: 0.25 | J15: 63.85 | K15: Tamil Nadu | L15: =IF(ISNUMBER(F15),F15,IFERROR(DATE(VALUE(RIGHT(F15,4)),VALUE(LEFT(F15,FIND("/",F15)-1)),VALUE(MID(F15,FIND("/",F15)+1,FIND("/",F15,FIND("/",F15)+1)-FIND("/",F15)-1))),"")) -> 42867 | M15: =YEAR(L15) -> 2017 | N15: =MONTH(L15) -> 5 | O15: =TEXT(L15,"yyyy-mm") -> 2017-05
A16: OD15 | B16: Sundar | C16: Eggs, Meat & Fish | D16: Chicken | E16: Kanyakumari | F16: 11/22/2016 | G16: Central | H16: 831 | I16: 0.22 | J16: 207.75 | K16: Tamil Nadu | L16: =IF(ISNUMBER(F16),F16,IFERROR(DATE(VALUE(RIGHT(F16,4)),VALUE(LEFT(F16,FIND("/",F16)-1)),VALUE(MID(F16,FIND("/",F16)+1,FIND("/",F16,FIND("/",F16)+1)-FIND("/",F16)-1))),"")) -> 42696 | M16: =YEAR(L16) -> 2016 | N16: =MONTH(L16) -> 11 | O16: =TEXT(L16,"yyyy-mm") -> 2016-11
A17: OD16 | B17: Ramesh | C17: Oil & Masala | D17: Edible Oil & Ghee | E17: Krishnagiri | F17: 11/22/2016 | G17: Central | H17: 1440 | I17: 0.11 | J17: 100.8 | K17: Tamil Nadu | L17: =IF(ISNUMBER(F17),F17,IFERROR(DATE(VALUE(RIGHT(F17,4)),VALUE(LEFT(F17,FIND("/",F17)-1)),VALUE(MID(F17,FIND("/",F17)+1,FIND("/",F17,FIND("/",F17)+1)-FIND("/",F17)-1))),"")) -> 42696 | M17: =YEAR(L17) -> 2016 | N17: =MONTH(L17) -> 11 | O17: =TEXT(L17,"yyyy-mm") -> 2016-11
A18: OD17 | B18: Alan | C18: Bakery | D18: Cakes | E18: Dharmapuri | F18: 42319 | G18: Central | H18: 1678 | I18: 0.28 | J18: 318.82 | K18: Tamil Nadu | L18: =IF(ISNUMBER(F18),F18,IFERROR(DATE(VALUE(RIGHT(F18,4)),VALUE(LEFT(F18,FIND("/",F18)-1)),VALUE(MID(F18,FIND("/",F18)+1,FIND("/",F18,FIND("/",F18)+1)-FIND("/",F18)-1))),"")) -> 42319 | M18: =YEAR(L18) -> 2015 | N18: =MONTH(L18) -> 11 | O18: =TEXT(L18,"yyyy-mm") -> 2015-11
A19: OD18 | B19: Arutra | C19: Beverages | D19: Health Drinks | E19: Bodi | F19: 5/13/2015 | G19: West | H19: 1617 | I19: 0.19 | J19: 113.19 | K19: Tamil Nadu | L19: =IF(ISNUMBER(F19),F19,IFERROR(DATE(VALUE(RIGHT(F19,4)),VALUE(LEFT(F19,FIND("/",F19)-1)),VALUE(MID(F19,FIND("/",F19)+1,FIND("/",F19,FIND("/",F19)+1)-FIND("/",F19)-1))),"")) -> 42137 | M19: =YEAR(L19) -> 2015 | N19: =MONTH(L19) -> 5 | O19: =TEXT(L19,"yyyy-mm") -> 2015-05
A20: OD19 | B20: Haseena | C20: Eggs, Meat & Fish | D20: Mutton | E20: Tenkasi | F20: 8/27/2015 | G20: West | H20: 1757 | I20: 0.35 | J20: 386.54 | K20: Tamil Nadu | L20: =IF(ISNUMBER(F20),F20,IFERROR(DATE(VALUE(RIGHT(F20,4)),VALUE(LEFT(F20,FIND("/",F20)-1)),VALUE(MID(F20,FIND("/",F20)+1,FIND("/",F20,FIND("/",F20)+1)-FIND("/",F20)-1))),"")) -> 42243 | M20: =YEAR(L20) -> 2015 | N20: =MONTH(L20) -> 8 | O20: =TEXT(L20,"yyyy-mm") -> 2015-08
A21: OD20 | B21: Verma | C21: Beverages | D21: Soft Drinks | E21: Kanyakumari | F21: 8/27/2015 | G21: West | H21: 692 | I21: 0.29 | J21: 159.16 | K21: Tamil Nadu | L21: =IF(ISNUMBER(F21),F21,IFERROR(DATE(VALUE(RIGHT(F21,4)),VALUE(LEFT(F21,FIND("/",F21)-1)),VALUE(MID(F21,FIND("/",F21)+1,FIND("/",F21,FIND("/",F21)+1)-FIND("/",F21)-1))),"")) -> 42243 | M21: =YEAR(L21) -> 2015 | N21: =MONTH(L21) -> 8 | O21: =TEXT(L21,"yyyy-mm") -> 2015-08
A22: OD21 | B22: Hafiz | C22: Beverages | D22: Health Drinks | E22: Vellore | F22: 8/27/2015 | G22: West | H22: 522 | I22: 0.19 | J22: 208.8 | K22: Tamil Nadu | L22: =IF(ISNUMBER(F22),F22,IFERROR(DATE(VALUE(RIGHT(F22,4)),VALUE(LEFT(F22,FIND("/",F22)-1)),VALUE(MID(F22,FIND("/",F22)+1,FIND("/",F22,FIND("/",F22)+1)-FIND("/",F22)-1))),"")) -> 42243 | M22: =YEAR(L22) -> 2015 | N22: =MONTH(L22) -> 8 | O22: =TEXT(L22,"yyyy-mm") -> 2015-08
A23: OD22 | B23: Alan | C23: Food Grains | D23: Dals & Pulses | E23: Karur | F23: 42990 | G23: Central | H23: 948 | I23: 0.13 | J23: 47.4 | K23: Tamil Nadu | L23: =IF(ISNUMBER(F23),F23,IFERROR(DATE(VALUE(RIGHT(F23,4)),VALUE(LEFT(F23,FIND("/",F23)-1)),VALUE(MID(F23,FIND("/",F23)+1,FIND("/",F23,FIND("/",F23)+1)-FIND("/",F23)-1))),"")) -> 42990 | M23: =YEAR(L23) -> 2017 | N23: =MONTH(L23) -> 9 | O23: =TEXT(L23,"yyyy-mm") -> 2017-09
A24: OD23 | B24: Haseena | C24: Beverages | D24: Soft Drinks | E24: Krishnagiri | F24: 42990 | G24: Central | H24: 707 | I24: 0.34 | J24: 148.47 | K24: Tamil Nadu | L24: =IF(ISNUMBER(F24),F24,IFERROR(DATE(VALUE(RIGHT(F24,4)),VALUE(LEFT(F24,FIND("/",F24)-1)),VALUE(MID(F24,FIND("/",F24)+1,FIND("/",F24,FIND("/",F24)+1)-FIND("/",F24)-1))),"")) -> 42990 | M24: =YEAR(L24) -> 2017 | N24: =MONTH(L24) -> 9 | O24: =TEXT(L24,"yyyy-mm") -> 2017-09
A25: OD24 | B25: Alan | C25: Fruits & Veggies | D25: Organic Vegetables | E25: Tenkasi | F25: 7/16/2018 | G25: East | H25: 969 | I25: 0.29 | J25: 77.52 | K25: Tamil Nadu | L25: =IF(ISNUMBER(F25),F25,IFERROR(DATE(VALUE(RIGHT(F25,4)),VALUE(LEFT(F25,FIND("/",F25)-1)),VALUE(MID(F25,FIND("/",F25)+1,FIND("/",F25,FIND("/",F25)+1)-FIND("/",F25)-1))),"")) -> 43297 | M25: =YEAR(L25) -> 2018 | N25: =MONTH(L25) -> 7 | O25: =TEXT(L25,"yyyy-mm") -> 2018-07
A26: OD25 | B26: Sharon | C26: Eggs, Meat & Fish | D26: Eggs | E26: Ooty | F26: 9/25/2016 | G26: West | H26: 1100 | I26: 0.11 | J26: 495 | K26: Tamil Nadu | L26: =IF(ISNUMBER(F26),F26,IFERROR(DATE(VALUE(RIGHT(F26,4)),VALUE(LEFT(F26,FIND("/",F26)-1)),VALUE(MID(F26,FIND("/",F26)+1,FIND("/",F26,FIND("/",F26)+1)-FIND("/",F26)-1))),"")) -> 42638 | M26: =YEAR(L26) -> 2016 | N26: =MONTH(L26) -> 9 | O26: =TEXT(L26,"yyyy-mm") -> 2016-09
A27: OD26 | B27: Krithika | C27: Snacks | D27: Chocolates | E27: Tirunelveli | F27: 1/16/2017 | G27: West | H27: 2022 | I27: 0.11 | J27: 202.2 | K27: Tamil Nadu | L27: =IF(ISNUMBER(F27),F27,IFERROR(DATE(VALUE(RIGHT(F27,4)),VALUE(LEFT(F27,FIND("/",F27)-1)),VALUE(MID(F27,FIND("/",F27)+1,FIND("/",F27,FIND("/",F27)+1)-FIND("/",F27)-1))),"")) -> 42751 | M27: =YEAR(L27) -> 2017 | N27: =MONTH(L27) -> 1 | O27: =TEXT(L27,"yyyy-mm") -> 2017-01
A28: OD27 | B28: Muneer | C28: Snacks | D28: Cookies | E28: Trichy | F28: 1/16/2017 | G28: West | H28: 541 | I28: 0.12 | J28: 43.28 | K28: Tamil Nadu | L28: =IF(ISNUMBER(F28),F28,IFERROR(DATE(VALUE(RIGHT(F28,4)),VALUE(LEFT(F28,FIND("/",F28)-1)),VALUE(MID(F28,FIND("/",F28)+1,FIND("/",F28,FIND("/",F28)+1)-FIND("/",F28)-1))),"")) -> 42751 | M28: =YEAR(L28) -> 2017 | N28: =MONTH(L28) -> 1 | O28: =TEXT(L28,"yyyy-mm") -> 2017-01
A29: OD28 | B29: Jackson | C29: Bakery | D29: Biscuits | E29: Viluppuram | F29: 9/17/2016 | G29: East | H29: 979 | I29: 0.22 | J29: 401.39 | K29: Tamil Nadu | L29: =IF(ISNUMBER(F29),F29,IFERROR(DATE(VALUE(RIGHT(F29,4)),VALUE(LEFT(F29,FIND("/",F29)-1)),VALUE(MID(F29,FIND("/",F29)+1,FIND("/",F29,FIND("/",F29)+1)-FIND("/",F29)-1))),"")) -> 42630 | M29: =YEAR(L29) -> 2016 | N29: =MONTH(L29) -> 9 | O29: =TEXT(L29,"yyyy-mm") -> 2016-09
A30: OD29 | B30: Veronica | C30: Beverages | D30: Soft Drinks | E30: Krishnagiri | F30: 9/17/2016 | G30: East | H30: 1988 | I30: 0.22 | J30: 874.72 | K30: Tamil Nadu | L30: =IF(ISNUMBER(F30),F30,IFERROR(DATE(VALUE(RIGHT(F30,4)),VALUE(LEFT(F30,FIND("/",F30)-1)),VALUE(MID(F30,FIND("/",F30)+1,FIND("/",F30,FIND("/",F30)+1)-FIND("/",F30)-1))),"")) -> 42630 | M30: =YEAR(L30) -> 2016 | N30: =MONTH(L30) -> 9 | O30: =TEXT(L30,"yyyy-mm") -> 2016-09
A31: OD30 | B31: Shah | C31: Oil & Masala | D31: Masalas | E31: Kanyakumari | F31: 9/17/2016 | G31: East | H31: 989 | I31: 0.17 | J31: 69.23 | K31: Tamil Nadu | L31: =IF(ISNUMBER(F31),F31,IFERROR(DATE(VALUE(RIGHT(F31,4)),VALUE(LEFT(F31,FIND("/",F31)-1)),VALUE(MID(F31,FIND("/",F31)+1,FIND("/",F31,FIND("/",F31)+1)-FIND("/",F31)-1))),"")) -> 42630 | M31: =YEAR(L31) -> 2016 | N31: =MONTH(L31) -> 9 | O31: =TEXT(L31,"yyyy-mm") -> 2016-09
A32: OD31 | B32: Ramesh | C32: Beverages | D32: Soft Drinks | E32: Dharmapuri | F32: 9/17/2016 | G32: East | H32: 1845 | I32: 0.24 | J32: 166.05 | K32: Tamil Nadu | L32: =IF(ISNUMBER(F32),F32,IFERROR(DATE(VALUE(RIGHT(F32,4)),VALUE(LEFT(F32,FIND("/",F32)-1)),VALUE(MID(F32,FIND("/",F32)+1,FIND("/",F32,FIND("/",F32)+1)-FIND("/",F32)-1))),"")) -> 42630 | M32: =YEAR(L32) -> 2016 | N32: =MONTH(L32) -> 9 | O32: =TEXT(L32,"yyyy-mm") -> 2016-09
A33: OD32 | B33: Mathew | C33: Snacks | D33: Noodles | E33: Vellore | F33: 9/17/2016 | G33: East | H33: 1400 | I33: 0.11 | J33: 420 | K33: Tamil Nadu | L33: =IF(ISNUMBER(F33),F33,IFERROR(DATE(VALUE(RIGHT(F33,4)),VALUE(LEFT(F33,FIND("/",F33)-1)),VALUE(MID(F33,FIND("/",F33)+1,FIND("/",F33,FIND("/",F33)+1)-FIND("/",F33)-1))),"")) -> 42630 | M33: =YEAR(L33) -> 2016 | N33: =MONTH(L33) -> 9 | O33: =TEXT(L33,"yyyy-mm") -> 2016-09
A34: OD33 | B34: Akash | C34: Oil & Masala | D34: Edible Oil & Ghee | E34: Trichy | F34: 9/17/2016 | G34: East | H34: 2163 | I34: 0.26 | J34: 670.53 | K34: Tamil Nadu | L34: =IF(ISNUMBER(F34),F34,IFERROR(DATE(VALUE(RIGHT(F34,4)),VALUE(LEFT(F34,FIND("/",F34)-1)),VALUE(MID(F34,FIND("/",F34)+1,FIND("/",F34,FIND("/",F34)+1)-FIND("/",F34)-1))),"")) -> 42630 | M34: =YEAR(L34) -> 2016 | N34: =MONTH(L34) -> 9 | O34: =TEXT(L34,"yyyy-mm") -> 2016-09
A35: OD34 | B35: Anu | C35: Oil & Masala | D35: Masalas | E35: Madurai | F35: 9/17/2016 | G35: East | H35: 1689 | I35: 0.34 | J35: 337.8 | K35: Tamil Nadu | L35: =IF(ISNUMBER(F35),F35,IFERROR(DATE(VALUE(RIGHT(F35,4)),VALUE(LEFT(F35,FIND("/",F35)-1)),VALUE(MID(F35,FIND("/",F35)+1,FIND("/",F35,FIND("/",F35)+1)-FIND("/",F35)-1))),"")) -> 42630 | M35: =YEAR(L35) -> 2016 | N35: =MONTH(L35) -> 9 | O35: =TEXT(L35,"yyyy-mm") -> 2016-09
A36: OD35 | B36: Anu | C36: Beverages | D36: Health Drinks | E36: Vellore | F36: 10/19/2018 | G36: Central | H36: 809 | I36: 0.32 | J36: 80.9 | K36: Tamil Nadu | L36: =IF(ISNUMBER(F36),F36,IFERROR(DATE(VALUE(RIGHT(F36,4)),VALUE(LEFT(F36,FIND("/",F36)-1)),VALUE(MID(F36,FIND("/",F36)+1,FIND("/",F36,FIND("/",F36)+1)-FIND("/",F36)-1))),"")) -> 43392 | M36: =YEAR(L36) -> 2018 | N36: =MONTH(L36) -> 10 | O36: =TEXT(L36,"yyyy-mm") -> 2018-10
A37: OD36 | B37: Sabeela | C37: Eggs, Meat & Fish | D37: Eggs | E37: Tirunelveli | F37: 42959 | G37: Central | H37: 1265 | I37: 0.22 | J37: 569.25 | K37: Tamil Nadu | L37: =IF(ISNUMBER(F37),F37,IFERROR(DATE(VALUE(RIGHT(F37,4)),VALUE(LEFT(F37,FIND("/",F37)-1)),VALUE(MID(F37,FIND("/",F37)+1,FIND("/",F37,FIND("/",F37)+1)-FIND("/",F37)-1))),"")) -> 42959 | M37: =YEAR(L37) -> 2017 | N37: =MONTH(L37) -> 8 | O37: =TEXT(L37,"yyyy-mm") -> 2017-08
A38: OD37 | B38: James | C38: Beverages | D38: Soft Drinks | E38: Salem | F38: 42959 | G38: Central | H38: 934 | I38: 0.35 | J38: 56.04 | K38: Tamil Nadu | L38: =IF(ISNUMBER(F38),F38,IFERROR(DATE(VALUE(RIGHT(F38,4)),VALUE(LEFT(F38,FIND("/",F38)-1)),VALUE(MID(F38,FIND("/",F38)+1,FIND("/",F38,FIND("/",F38)+1)-FIND("/",F38)-1))),"")) -> 42959 | M38: =YEAR(L38) -> 2017 | N38: =MONTH(L38) -> 8 | O38: =TEXT(L38,"yyyy-mm") -> 2017-08
A39: OD38 | B39: Willams | C39: Fruits & Veggies | D39: Organic Vegetables | E39: Ramanadhapuram | F39: 12/27/2016 | G39: Central | H39: 1354 | I39: 0.16 | J39: 446.82 | K39: Tamil Nadu | L39: =IF(ISNUMBER(F39),F39,IFERROR(DATE(VALUE(RIGHT(F39,4)),VALUE(LEFT(F39,FIND("/",F39)-1)),VALUE(MID(F39,FIND("/",F39)+1,FIND("/",F39,FIND("/",F39)+1)-FIND("/",F39)-1))),"")) -> 42731 | M39: =YEAR(L39) -> 2016 | N39: =MONTH(L39) -> 12 | O39: =TEXT(L39,"yyyy-mm") -> 2016-12
A40: OD39 | B40: Jonas | C40: Fruits & Veggies | D40: Fresh Fruits | E40: Chennai | F40: 12/27/2016 | G40: Central | H40: 1751 | I40: 0.19 | J40: 280.16 | K40: Tamil Nadu | L40: =IF(ISNUMBER(F40),F40,IFERROR(DATE(VALUE(RIGHT(F40,4)),VALUE(LEFT(F40,FIND("/",F40)-1)),VALUE(MID(F40,FIND("/",F40)+1,FIND("/",F40,FIND("/",F40)+1)-FIND("/",F40)-1))),"")) -> 42731 | M40: =YEAR(L40) -> 2016 | N40: =MONTH(L40) -> 12 | O40: =TEXT(L40,"yyyy-mm") -> 2016-12
A41: OD40 | B41: Sabeela | C41: Eggs, Meat & Fish | D41: Chicken | E41: Cumbum | F41: 12/27/2016 | G41: Central | H41: 2045 | I41: 0.23 | J41: 879.35 | K41: Tamil Nadu | L41: =IF(ISNUMBER(F41),F41,IFERROR(DATE(VALUE(RIGHT(F41,4)),VALUE(LEFT(F41,FIND("/",F41)-1)),VALUE(MID(F41,FIND("/",F41)+1,FIND("/",F41,FIND("/",F41)+1)-FIND("/",F41)-1))),"")) -> 42731 | M41: =YEAR(L41) -> 2016 | N41: =MONTH(L41) -> 12 | O41: =TEXT(L41,"yyyy-mm") -> 2016-12
A42: OD41 | B42: Malik | C42: Beverages | D42: Health Drinks | E42: Namakkal | F42: 12/27/2016 | G42: Central | H42: 660 | I42: 0.19 | J42: 92.4 | K42: Tamil Nadu | L42: =IF(ISNUMBER(F42),F42,IFERROR(DATE(VALUE(RIGHT(F42,4)),VALUE(LEFT(F42,FIND("/",F42)-1)),VALUE(MID(F42,FIND("/",F42)+1,FIND("/",F42,FIND("/",F42)+1)-FIND("/",F42)-1))),"")) -> 42731 | M42: =YEAR(L42) -> 2016 | N42: =MONTH(L42) -> 12 | O42: =TEXT(L42,"yyyy-mm") -> 2016-12
A43: OD42 | B43: Arutra | C43: Beverages | D43: Soft Drinks | E43: Salem | F43: 43382 | G43: Central | H43: 1868 | I43: 0.18 | J43: 616.44 | K43: Tamil Nadu | L43: =IF(ISNUMBER(F43),F43,IFERROR(DATE(VALUE(RIGHT(F43,4)),VALUE(LEFT(F43,FIND("/",F43)-1)),VALUE(MID(F43,FIND("/",F43)+1,FIND("/",F43,FIND("/",F43)+1)-FIND("/",F43)-1))),"")) -> 43382 | M43: =YEAR(L43) -> 2018 | N43: =MONTH(L43) -> 10 | O43: =TEXT(L43,"yyyy-mm") -> 2018-10
A44: OD43 | B44: Sharon | C44: Snacks | D44: Cookies | E44: Bodi | F44: 7/17/2017 | G44: West | H44: 1017 | I44: 0.25 | J44: 345.78 | K44: Tamil Nadu | L44: =IF(ISNUMBER(F44),F44,IFERROR(DATE(VALUE(RIGHT(F44,4)),VALUE(LEFT(F44,FIND("/",F44)-1)),VALUE(MID(F44,FIND("/",F44)+1,FIND("/",F44,FIND("/",F44)+1)-FIND("/",F44)-1))),"")) -> 42933 | M44: =YEAR(L44) -> 2017 | N44: =MONTH(L44) -> 7 | O44: =TEXT(L44,"yyyy-mm") -> 2017-07
A45: OD44 | B45: Mathew | C45: Snacks | D45: Cookies | E45: Dharmapuri | F45: 9/19/2018 | G45: South | H45: 2311 | I45: 0.2 | J45: 1039.95 | K45: Tamil Nadu | L45: =IF(ISNUMBER(F45),F45,IFERROR(DATE(VALUE(RIGHT(F45,4)),VALUE(LEFT(F45,FIND("/",F45)-1)),VALUE(MID(F45,FIND("/",F45)+1,FIND("/",F45,FIND("/",F45)+1)-FIND("/",F45)-1))),"")) -> 43362 | M45: =YEAR(L45) -> 2018 | N45: =MONTH(L45) -> 9 | O45: =TEXT(L45,"yyyy-mm") -> 2018-09
A46: OD45 | B46: Amrish | C46: Bakery | D46: Biscuits | E46: Krishnagiri | F46: 43042 | G46: Central | H46: 1663 | I46: 0.17 | J46: 731.72 | K46: Tamil Nadu | L46: =IF(ISNUMBER(F46),F46,IFERROR(DATE(VALUE(RIGHT(F46,4)),VALUE(LEFT(F46,FIND("/",F46)-1)),VALUE(MID(F46,FIND("/",F46)+1,FIND("/",F46,FIND("/",F46)+1)-FIND("/",F46)-1))),"")) -> 43042 | M46: =YEAR(L46) -> 2017 | N46: =MONTH(L46) -> 11 | O46: =TEXT(L46,"yyyy-mm") -> 2017-11
A47: OD46 | B47: Vince | C47: Eggs, Meat & Fish | D47: Eggs | E47: Madurai | F47: 43042 | G47: Central | H47: 1420 | I47: 0.19 | J47: 355 | K47: Tamil Nadu | L47: =IF(ISNUMBER(F47),F47,IFERROR(DATE(VALUE(RIGHT(F47,4)),VALUE(LEFT(F47,FIND("/",F47)-1)),VALUE(MID(F47,FIND("/",F47)+1,FIND("/",F47,FIND("/",F47)+1)-FIND("/",F47)-1))),"")) -> 43042 | M47: =YEAR(L47) -> 2017 | N47: =MONTH(L47) -> 11 | O47: =TEXT(L47,"yyyy-mm") -> 2017-11
A48: OD47 | B48: Suresh | C48: Fruits & Veggies | D48: Organic Vegetables | E48: Nagercoil | F48: 10/20/2015 | G48: Central | H48: 1415 | I48: 0.31 | J48: 509.4 | K48: Tamil Nadu | L48: =IF(ISNUMBER(F48),F48,IFERROR(DATE(VALUE(RIGHT(F48,4)),VALUE(LEFT(F48,FIND("/",F48)-1)),VALUE(MID(F48,FIND("/",F48)+1,FIND("/",F48,FIND("/",F48)+1)-FIND("/",F48)-1))),"")) -> 42297 | M48: =YEAR(L48) -> 2015 | N48: =MONTH(L48) -> 10 | O48: =TEXT(L48,"yyyy-mm") -> 2015-10
A49: OD48 | B49: Mathew | C49: Snacks | D49: Noodles | E49: Chennai | F49: 6/20/2017 | G49: East | H49: 1488 | I49: 0.3 | J49: 610.08 | K49: Tamil Nadu | L49: =IF(ISNUMBER(F49),F49,IFERROR(DATE(VALUE(RIGHT(F49,4)),VALUE(LEFT(F49,FIND("/",F49)-1)),VALUE(MID(F49,FIND("/",F49)+1,FIND("/",F49,FIND("/",F49)+1)-FIND("/",F49)-1))),"")) -> 42906 | M49: =YEAR(L49) -> 2017 | N49: =MONTH(L49) -> 6 | O49: =TEXT(L49,"yyyy-mm") -> 2017-06
A50: OD49 | B50: Ridhesh | C50: Snacks | D50: Noodles | E50: Pudukottai | F50: 6/20/2017 | G50: East | H50: 726 | I50: 0.18 | J50: 43.56 | K50: Tamil Nadu | L50: =IF(ISNUMBER(F50),F50,IFERROR(DATE(VALUE(RIGHT(F50,4)),VALUE(LEFT(F50,FIND("/",F50)-1)),VALUE(MID(F50,FIND("/",F50)+1,FIND("/",F50,FIND("/",F50)+1)-FIND("/",F50)-1))),"")) -> 42906 | M50: =YEAR(L50) -> 2017 | N50: =MONTH(L50) -> 6 | O50: =TEXT(L50,"yyyy-mm") -> 2017-06
A51: OD50 | B51: Amrish | C51: Bakery | D51: Cakes | E51: Ooty | F51: 4/18/2016 | G51: Central | H51: 1259 | I51: 0.15 | J51: 415.47 | K51: Tamil Nadu | L51: =IF(ISNUMBER(F51),F51,IFERROR(DATE(VALUE(RIGHT(F51,4)),VALUE(LEFT(F51,FIND("/",F51)-1)),VALUE(MID(F51,FIND("/",F51)+1,FIND("/",F51,FIND("/",F51)+1)-FIND("/",F51)-1))),"")) -> 42478 | M51: =YEAR(L51) -> 2016 | N51: =MONTH(L51) -> 4 | O51: =TEXT(L51,"yyyy-mm") -> 2016-04
A52: OD51 | B52: Esther | C52: Beverages | D52: Soft Drinks | E52: Salem | F52: 4/18/2016 | G52: Central | H52: 902 | I52: 0.29 | J52: 153.34 | K52: Tamil Nadu | L52: =IF(ISNUMBER(F52),F52,IFERROR(DATE(VALUE(RIGHT(F52,4)),VALUE(LEFT(F52,FIND("/",F52)-1)),VALUE(MID(F52,FIND("/",F52)+1,FIND("/",F52,FIND("/",F52)+1)-FIND("/",F52)-1))),"")) -> 42478 | M52: =YEAR(L52) -> 2016 | N52: =MONTH(L52) -> 4 | O52: =TEXT(L52,"yyyy-mm") -> 2016-04
A53: OD52 | B53: Shah | C53: Beverages | D53: Soft Drinks | E53: Salem | F53: 4/18/2016 | G53: Central | H53: 2306 | I53: 0.3 | J53: 553.44 | K53: Tamil Nadu | L53: =IF(ISNUMBER(F53),F53,IFERROR(DATE(VALUE(RIGHT(F53,4)),VALUE(LEFT(F53,FIND("/",F53)-1)),VALUE(MID(F53,FIND("/",F53)+1,FIND("/",F53,FIND("/",F53)+1)-FIND("/",F53)-1))),"")) -> 42478 | M53: =YEAR(L53) -> 2016 | N53: =MONTH(L53) -> 4 | O53: =TEXT(L53,"yyyy-mm") -> 2016-04
A54: OD53 | B54: Sudha | C54: Bakery | D54: Cakes | E54: Theni | F54: 4/18/2016 | G54: Central | H54: 1417 | I54: 0.19 | J54: 99.19 | K54: Tamil Nadu | L54: =IF(ISNUMBER(F54),F54,IFERROR(DATE(VALUE(RIGHT(F54,4)),VALUE(LEFT(F54,FIND("/",F54)-1)),VALUE(MID(F54,FIND("/",F54)+1,FIND("/",F54,FIND("/",F54)+1)-FIND("/",F54)-1))),"")) -> 42478 | M54: =YEAR(L54) -> 2016 | N54: =MONTH(L54) -> 4 | O54: =TEXT(L54,"yyyy-mm") -> 2016-04
A55: OD54 | B55: Yusuf | C55: Fruits & Veggies | D55: Fresh Vegetables | E55: Madurai | F55: 43051 | G55: East | H55: 627 | I55: 0.33 | J55: 181.83 | K55: Tamil Nadu | L55: =IF(ISNUMBER(F55),F55,IFERROR(DATE(VALUE(RIGHT(F55,4)),VALUE(LEFT(F55,FIND("/",F55)-1)),VALUE(MID(F55,FIND("/",F55)+1,FIND("/",F55,FIND("/",F55)+1)-FIND("/",F55)-1))),"")) -> 43051 | M55: =YEAR(L55) -> 2017 | N55: =MONTH(L55) -> 11 | O55: =TEXT(L55,"yyyy-mm") -> 2017-11
A56: OD55 | B56: Esther | C56: Fruits & Veggies | D56: Organic Fruits | E56: Nagercoil | F56: 43051 | G56: East | H56: 760 | I56: 0.28 | J56: 60.8 | K56: Tamil Nadu | L56: =IF(ISNUMBER(F56),F56,IFERROR(DATE(VALUE(RIGHT(F56,4)),VALUE(LEFT(F56,FIND("/",F56)-1)),VALUE(MID(F56,FIND("/",F56)+1,FIND("/",F56,FIND("/",F56)+1)-FIND("/",F56)-1))),"")) -> 43051 | M56: =YEAR(L56) -> 2017 | N56: =MONTH(L56) -> 11 | O56: =TEXT(L56,"yyyy-mm") -> 2017-11
A57: OD56 | B57: Muneer | C57: Food Grains | D57: Atta & Flour | E57: Salem | F57: 6/17/2017 | G57: East | H57: 2350 | I57: 0.15 | J57: 611 | K57: Tamil Nadu | L57: =IF(ISNUMBER(F57),F57,IFERROR(DATE(VALUE(RIGHT(F57,4)),VALUE(LEFT(F57,FIND("/",F57)-1)),VALUE(MID(F57,FIND("/",F57)+1,FIND("/",F57,FIND("/",F57)+1)-FIND("/",F57)-1))),"")) -> 42903 | M57: =YEAR(L57) -> 2017 | N57: =MONTH(L57) -> 6 | O57: =TEXT(L57,"yyyy-mm") -> 2017-06
A58: OD57 | B58: Komal | C58: Eggs, Meat & Fish | D58: Fish | E58: Krishnagiri | F58: 6/17/2017 | G58: East | H58: 1179 | I58: 0.34 | J58: 271.17 | K58: Tamil Nadu | L58: =IF(ISNUMBER(F58),F58,IFERROR(DATE(VALUE(RIGHT(F58,4)),VALUE(LEFT(F58,FIND("/",F58)-1)),VALUE(MID(F58,FIND("/",F58)+1,FIND("/",F58,FIND("/",F58)+1)-FIND("/",F58)-1))),"")) -> 42903 | M58: =YEAR(L58) -> 2017 | N58: =MONTH(L58) -> 6 | O58: =TEXT(L58,"yyyy-mm") -> 2017-06
A59: OD58 | B59: Veena | C59: Food Grains | D59: Dals & Pulses | E59: Trichy | F59: 6/17/2017 | G59: East | H59: 1624 | I59: 0.35 | J59: 194.88 | K59: Tamil Nadu | L59: =IF(ISNUMBER(F59),F59,IFERROR(DATE(VALUE(RIGHT(F59,4)),VALUE(LEFT(F59,FIND("/",F59)-1)),VALUE(MID(F59,FIND("/",F59)+1,FIND("/",F59,FIND("/",F59)+1)-FIND("/",F59)-1))),"")) -> 42903 | M59: =YEAR(L59) -> 2017 | N59: =MONTH(L59) -> 6 | O59: =TEXT(L59,"yyyy-mm") -> 2017-06
A60: OD59 | B60: Sharon | C60: Eggs, Meat & Fish | D60: Mutton | E60: Trichy | F60: 6/17/2017 | G60: East | H60: 1316 | I60: 0.35 | J60: 421.12 | K60: Tamil Nadu | L60: =IF(ISNUMBER(F60),F60,IFERROR(DATE(VALUE(RIGHT(F60,4)),VALUE(LEFT(F60,FIND("/",F60)-1)),VALUE(MID(F60,FIND("/",F60)+1,FIND("/",F60,FIND("/",F60)+1)-FIND("/",F60)-1))),"")) -> 42903 | M60: =YEAR(L60) -> 2017 | N60: =MONTH(L60) -> 6 | O60: =TEXT(L60,"yyyy-mm") -> 2017-06
A61: OD60 | B61: Shree | C61: Beverages | D61: Health Drinks | E61: Coimbatore | F61: 6/17/2017 | G61: East | H61: 2121 | I61: 0.12 | J61: 678.72 | K61: Tamil Nadu | L61: =IF(ISNUMBER(F61),F61,IFERROR(DATE(VALUE(RIGHT(F61,4)),VALUE(LEFT(F61,FIND("/",F61)-1)),VALUE(MID(F61,FIND("/",F61)+1,FIND("/",F61,FIND("/",F61)+1)-FIND("/",F61)-1))),"")) -> 42903 | M61: =YEAR(L61) -> 2017 | N61: =MONTH(L61) -> 6 | O61: =TEXT(L61,"yyyy-mm") -> 2017-06
A62: OD61 | B62: Roshan | C62: Oil & Masala | D62: Masalas | E62: Virudhunagar | F62: 6/17/2017 | G62: East | H62: 1428 | I62: 0.28 | J62: 271.32 | K62: Tamil Nadu | L62: =IF(ISNUMBER(F62),F62,IFERROR(DATE(VALUE(RIGHT(F62,4)),VALUE(LEFT(F62,FIND("/",F62)-1)),VALUE(MID(F62,FIND("/",F62)+1,FIND("/",F62,FIND("/",F62)+1)-FIND("/",F62)-1))),"")) -> 42903 | M62: =YEAR(L62) -> 2017 | N62: =MONTH(L62) -> 6 | O62: =TEXT(L62,"yyyy-mm") -> 2017-06
A63: OD62 | B63: Willams | C63: Snacks | D63: Noodles | E63: Perambalur | F63: 6/17/2017 | G63: East | H63: 706 | I63: 0.33 | J63: 289.46 | K63: Tamil Nadu | L63: =IF(ISNUMBER(F63),F63,IFERROR(DATE(VALUE(RIGHT(F63,4)),VALUE(LEFT(F63,FIND("/",F63)-1)),VALUE(MID(F63,FIND("/",F63)+1,FIND("/",F63,FIND("/",F63)+1)-FIND("/",F63)-1))),"")) -> 42903 | M63: =YEAR(L63) -> 2017 | N63: =MONTH(L63) -> 6 | O63: =TEXT(L63,"yyyy-mm") -> 2017-06
A64: OD63 | B64: Sudeep | C64: Eggs, Meat & Fish | D64: Fish | E64: Dharmapuri | F64: 11/24/2016 | G64: West | H64: 921 | I64: 0.25 | J64: 184.2 | K64: Tamil Nadu | L64: =IF(ISNUMBER(F64),F64,IFERROR(DATE(VALUE(RIGHT(F64,4)),VALUE(LEFT(F64,FIND("/",F64)-1)),VALUE(MID(F64,FIND("/",F64)+1,FIND("/",F64,FIND("/",F64)+1)-FIND("/",F64)-1))),"")) -> 42698 | M64: =YEAR(L64) -> 2016 | N64: =MONTH(L64) -> 11 | O64: =TEXT(L64,"yyyy-mm") -> 2016-11
A65: OD64 | B65: Yusuf | C65: Fruits & Veggies | D65: Fresh Fruits | E65: Trichy | F65: 11/24/2016 | G65: West | H65: 1741 | I65: 0.31 | J65: 661.58 | K65: Tamil Nadu | L65: =IF(ISNUMBER(F65),F65,IFERROR(DATE(VALUE(RIGHT(F65,4)),VALUE(LEFT(F65,FIND("/",F65)-1)),VALUE(MID(F65,FIND("/",F65)+1,FIND("/",F65,FIND("/",F65)+1)-FIND("/",F65)-1))),"")) -> 42698 | M65: =YEAR(L65) -> 2016 | N65: =MONTH(L65) -> 11 | O65: =TEXT(L65,"yyyy-mm") -> 2016-11
A66: OD65 | B66: Willams | C66: Eggs, Meat & Fish | D66: Eggs | E66: Madurai | F66: 11/24/2016 | G66: West | H66: 607 | I66: 0.22 | J66: 200.31 | K66: Tamil Nadu | L66: =IF(ISNUMBER(F66),F66,IFERROR(DATE(VALUE(RIGHT(F66,4)),VALUE(LEFT(F66,FIND("/",F66)-1)),VALUE(MID(F66,FIND("/",F66)+1,FIND("/",F66,FIND("/",F66)+1)-FIND("/",F66)-1))),"")) -> 42698 | M66: =YEAR(L66) -> 2016 | N66: =MONTH(L66) -> 11 | O66: =TEXT(L66,"yyyy-mm") -> 2016-11
A67: OD66 | B67: Muneer | C67: Eggs, Meat & Fish | D67: Mutton | E67: Tirunelveli | F67: 11/24/2016 | G67: West | H67: 1824 | I67: 0.25 | J67: 766.08 | K67: Tamil Nadu | L67: =IF(ISNUMBER(F67),F67,IFERROR(DATE(VALUE(RIGHT(F67,4)),VALUE(LEFT(F67,FIND("/",F67)-1)),VALUE(MID(F67,FIND("/",F67)+1,FIND("/",F67,FIND("/",F67)+1)-FIND("/",F67)-1))),"")) -> 42698 | M67: =YEAR(L67) -> 2016 | N67: =MONTH(L67) -> 11 | O67: =TEXT(L67,"yyyy-mm") -> 2016-11
A68: OD67 | B68: Vinne | C68: Food Grains | D68: Atta & Flour | E68: Madurai | F68: 4/30/2016 | G68: Central | H68: 1368 | I68: 0.11 | J68: 383.04 | K68: Tamil Nadu | L68: =IF(ISNUMBER(F68),F68,IFERROR(DATE(VALUE(RIGHT(F68,4)),VALUE(LEFT(F68,FIND("/",F68)-1)),VALUE(MID(F68,FIND("/",F68)+1,FIND("/",F68,FIND("/",F68)+1)-FIND("/",F68)-1))),"")) -> 42490 | M68: =YEAR(L68) -> 2016 | N68: =MONTH(L68) -> 4 | O68: =TEXT(L68,"yyyy-mm") -> 2016-04
A69: OD68 | B69: Roshan | C69: Fruits & Veggies | D69: Fresh Vegetables | E69: Pudukottai | F69: 42136 | G69: West | H69: 1160 | I69: 0.16 | J69: 510.4 | K69: Tamil Nadu | L69: =IF(ISNUMBER(F69),F69,IFERROR(DATE(VALUE(RIGHT(F69,4)),VALUE(LEFT(F69,FIND("/",F69)-1)),VALUE(MID(F69,FIND("/",F69)+1,FIND("/",F69,FIND("/",F69)+1)-FIND("/",F69)-1))),"")) -> 42136 | M69: =YEAR(L69) -> 2015 | N69: =MONTH(L69) -> 5 | O69: =TEXT(L69,"yyyy-mm") -> 2015-05
A70: OD69 | B70: Ramesh | C70: Food Grains | D70: Atta & Flour | E70: Viluppuram | F70: 42136 | G70: West | H70: 1294 | I70: 0.23 | J70: 77.64 | K70: Tamil Nadu | L70: =IF(ISNUMBER(F70),F70,IFERROR(DATE(VALUE(RIGHT(F70,4)),VALUE(LEFT(F70,FIND("/",F70)-1)),VALUE(MID(F70,FIND("/",F70)+1,FIND("/",F70,FIND("/",F70)+1)-FIND("/",F70)-1))),"")) -> 42136 | M70: =YEAR(L70) -> 2015 | N70: =MONTH(L70) -> 5 | O70: =TEXT(L70,"yyyy-mm") -> 2015-05
A71: OD70 | B71: Peer | C71: Oil & Masala | D71: Masalas | E71: Ooty | F71: 42831 | G71: South | H71: 1232 | I71: 0.14 | J71: 554.4 | K71: Tamil Nadu | L71: =IF(ISNUMBER(F71),F71,IFERROR(DATE(VALUE(RIGHT(F71,4)),VALUE(LEFT(F71,FIND("/",F71)-1)),VALUE(MID(F71,FIND("/",F71)+1,FIND("/",F71,FIND("/",F71)+1)-FIND("/",F71)-1))),"")) -> 42831 | M71: =YEAR(L71) -> 2017 | N71: =MONTH(L71) -> 4 | O71: =TEXT(L71,"yyyy-mm") -> 2017-04
A72: OD71 | B72: Verma | C72: Eggs, Meat & Fish | D72: Mutton | E72: Kanyakumari | F72: 9/18/2017 | G72: East | H72: 994 | I72: 0.31 | J72: 357.84 | K72: Tamil Nadu | L72: =IF(ISNUMBER(F72),F72,IFERROR(DATE(VALUE(RIGHT(F72,4)),VALUE(LEFT(F72,FIND("/",F72)-1)),VALUE(MID(F72,FIND("/",F72)+1,FIND("/",F72,FIND("/",F72)+1)-FIND("/",F72)-1))),"")) -> 42996 | M72: =YEAR(L72) -> 2017 | N72: =MONTH(L72) -> 9 | O72: =TEXT(L72,"yyyy-mm") -> 2017-09
A73: OD72 | B73: Yusuf | C73: Snacks | D73: Noodles | E73: Kanyakumari | F73: 9/14/2018 | G73: Central | H73: 2468 | I73: 0.18 | J73: 1011.88 | K73: Tamil Nadu | L73: =IF(ISNUMBER(F73),F73,IFERROR(DATE(VALUE(RIGHT(F73,4)),VALUE(LEFT(F73,FIND("/",F73)-1)),VALUE(MID(F73,FIND("/",F73)+1,FIND("/",F73,FIND("/",F73)+1)-FIND("/",F73)-1))),"")) -> 43357 | M73: =YEAR(L73) -> 2018 | N73: =MONTH(L73) -> 9 | O73: =TEXT(L73,"yyyy-mm") -> 2018-09
A74: OD73 | B74: Alan | C74: Snacks | D74: Cookies | E74: Theni | F74: 4/26/2016 | G74: South | H74: 721 | I74: 0.27 | J74: 100.94 | K74: Tamil Nadu | L74: =IF(ISNUMBER(F74),F74,IFERROR(DATE(VALUE(RIGHT(F74,4)),VALUE(LEFT(F74,FIND("/",F74)-1)),VALUE(MID(F74,FIND("/",F74)+1,FIND("/",F74,FIND("/",F74)+1)-FIND("/",F74)-1))),"")) -> 42486 | M74: =YEAR(L74) -> 2016 | N74: =MONTH(L74) -> 4 | O74: =TEXT(L74,"yyyy-mm") -> 2016-04
A75: OD74 | B75: Vidya | C75: Fruits & Veggies | D75: Organic Vegetables | E75: Vellore | F75: 4/26/2016 | G75: South | H75: 2375 | I75: 0.21 | J75: 475 | K75: Tamil Nadu | L75: =IF(ISNUMBER(F75),F75,IFERROR(DATE(VALUE(RIGHT(F75,4)),VALUE(LEFT(F75,FIND("/",F75)-1)),VALUE(MID(F75,FIND("/",F75)+1,FIND("/",F75,FIND("/",F75)+1)-FIND("/",F75)-1))),"")) -> 42486 | M75: =YEAR(L75) -> 2016 | N75: =MONTH(L75) -> 4 | O75: =TEXT(L75,"yyyy-mm") -> 2016-04
A76: OD75 | B76: Arvind | C76: Beverages | D76: Soft Drinks | E76: Vellore | F76: 4/26/2016 | G76: South | H76: 1965 | I76: 0.13 | J76: 117.9 | K76: Tamil Nadu | L76: =IF(ISNUMBER(F76),F76,IFERROR(DATE(VALUE(RIGHT(F76,4)),VALUE(LEFT(F76,FIND("/",F76)-1)),VALUE(MID(F76,FIND("/",F76)+1,FIND("/",F76,FIND("/",F76)+1)-FIND("/",F76)-1))),"")) -> 42486 | M76: =YEAR(L76) -> 2016 | N76: =MONTH(L76) -> 4 | O76: =TEXT(L76,"yyyy-mm") -> 2016-04
A77: OD76 | B77: Veronica | C77: Beverages | D77: Soft Drinks | E77: Bodi | F77: 43355 | G77: Central | H77: 1489 | I77: 0.12 | J77: 193.57 | K77: Tamil Nadu | L77: =IF(ISNUMBER(F77),F77,IFERROR(DATE(VALUE(RIGHT(F77,4)),VALUE(LEFT(F77,FIND("/",F77)-1)),VALUE(MID(F77,FIND("/",F77)+1,FIND("/",F77,FIND("/",F77)+1)-FIND("/",F77)-1))),"")) -> 43355 | M77: =YEAR(L77) -> 2018 | N77: =MONTH(L77) -> 9 | O77: =TEXT(L77,"yyyy-mm") -> 2018-09
A78: OD77 | B78: Arvind | C78: Fruits & Veggies | D78: Organic Fruits | E78: Ooty | F78: 43355 | G78: Central | H78: 1250 | I78: 0.27 | J78: 75 | K78: Tamil Nadu | L78: =IF(ISNUMBER(F78),F78,IFERROR(DATE(VALUE(RIGHT(F78,4)),VALUE(LEFT(F78,FIND("/",F78)-1)),VALUE(MID(F78,FIND("/",F78)+1,FIND("/",F78,FIND("/",F78)+1)-FIND("/",F78)-1))),"")) -> 43355 | M78: =YEAR(L78) -> 2018 | N78: =MONTH(L78) -> 9 | O78: =TEXT(L78,"yyyy-mm") -> 2018-09
A79: OD78 | B79: Anu | C79: Snacks | D79: Noodles | E79: Coimbatore | F79: 43355 | G79: Central | H79: 1358 | I79: 0.31 | J79: 488.88 | K79: Tamil Nadu | L79: =IF(ISNUMBER(F79),F79,IFERROR(DATE(VALUE(RIGHT(F79,4)),VALUE(LEFT(F79,FIND("/",F79)-1)),VALUE(MID(F79,FIND("/",F79)+1,FIND("/",F79,FIND("/",F79)+1)-FIND("/",F79)-1))),"")) -> 43355 | M79: =YEAR(L79) -> 2018 | N79: =MONTH(L79) -> 9 | O79: =TEXT(L79,"yyyy-mm") -> 2018-09
A80: OD79 | B80: Haseena | C80: Snacks | D80: Cookies | E80: Vellore | F80: 11/26/2015 | G80: Central | H80: 719 | I80: 0.2 | J80: 64.71 | K80: Tamil Nadu | L80: =IF(ISNUMBER(F80),F80,IFERROR(DATE(VALUE(RIGHT(F80,4)),VALUE(LEFT(F80,FIND("/",F80)-1)),VALUE(MID(F80,FIND("/",F80)+1,FIND("/",F80,FIND("/",F80)+1)-FIND("/",F80)-1))),"")) -> 42334 | M80: =YEAR(L80) -> 2015 | N80: =MONTH(L80) -> 11 | O80: =TEXT(L80,"yyyy-mm") -> 2015-11
A81: OD80 | B81: Veena | C81: Fruits & Veggies | D81: Organic Fruits | E81: Chennai | F81: 43075 | G81: South | H81: 2303 | I81: 0.26 | J81: 621.81 | K81: Tamil Nadu | L81: =IF(ISNUMBER(F81),F81,IFERROR(DATE(VALUE(RIGHT(F81,4)),VALUE(LEFT(F81,FIND("/",F81)-1)),VALUE(MID(F81,FIND("/",F81)+1,FIND("/",F81,FIND("/",F81)+1)-FIND("/",F81)-1))),"")) -> 43075 | M81: =YEAR(L81) -> 2017 | N81: =MONTH(L81) -> 12 | O81: =TEXT(L81,"yyyy-mm") -> 2017-12
A82: OD81 | B82: Kumar | C82: Beverages | D82: Health Drinks | E82: Kanyakumari | F82: 43075 | G82: South | H82: 2027 | I82: 0.34 | J82: 912.15 | K82: Tamil Nadu | L82: =IF(ISNUMBER(F82),F82,IFERROR(DATE(VALUE(RIGHT(F82,4)),VALUE(LEFT(F82,FIND("/",F82)-1)),VALUE(MID(F82,FIND("/",F82)+1,FIND("/",F82,FIND("/",F82)+1)-FIND("/",F82)-1))),"")) -> 43075 | M82: =YEAR(L82) -> 2017 | N82: =MONTH(L82) -> 12 | O82: =TEXT(L82,"yyyy-mm") -> 2017-12
A83: OD82 | B83: Amy | C83: Food Grains | D83: Atta & Flour | E83: Bodi | F83: 42348 | G83: West | H83: 1739 | I83: 0.29 | J83: 765.16 | K83: Tamil Nadu | L83: =IF(ISNUMBER(F83),F83,IFERROR(DATE(VALUE(RIGHT(F83,4)),VALUE(LEFT(F83,FIND("/",F83)-1)),VALUE(MID(F83,FIND("/",F83)+1,FIND("/",F83,FIND("/",F83)+1)-FIND("/",F83)-1))),"")) -> 42348 | M83: =YEAR(L83) -> 2015 | N83: =MONTH(L83) -> 12 | O83: =TEXT(L83,"yyyy-mm") -> 2015-12
A84: OD83 | B84: Komal | C84: Oil & Masala | D84: Spices | E84: Cumbum | F84: 42348 | G84: West | H84: 990 | I84: 0.26 | J84: 227.7 | K84: Tamil Nadu | L84: =IF(ISNUMBER(F84),F84,IFERROR(DATE(VALUE(RIGHT(F84,4)),VALUE(LEFT(F84,FIND("/",F84)-1)),VALUE(MID(F84,FIND("/",F84)+1,FIND("/",F84,FIND("/",F84)+1)-FIND("/",F84)-1))),"")) -> 42348 | M84: =YEAR(L84) -> 2015 | N84: =MONTH(L84) -> 12 | O84: =TEXT(L84,"yyyy-mm") -> 2015-12
A85: OD84 | B85: Ravi | C85: Beverages | D85: Soft Drinks | E85: Dharmapuri | F85: 42438 | G85: South | H85: 2354 | I85: 0.11 | J85: 682.66 | K85: Tamil Nadu | L85: =IF(ISNUMBER(F85),F85,IFERROR(DATE(VALUE(RIGHT(F85,4)),VALUE(LEFT(F85,FIND("/",F85)-1)),VALUE(MID(F85,FIND("/",F85)+1,FIND("/",F85,FIND("/",F85)+1)-FIND("/",F85)-1))),"")) -> 42438 | M85: =YEAR(L85) -> 2016 | N85: =MONTH(L85) -> 3 | O85: =TEXT(L85,"yyyy-mm") -> 2016-03
A86: OD85 | B86: Amy | C86: Fruits & Veggies | D86: Organic Fruits | E86: Bodi | F86: 11/13/2018 | G86: Central | H86: 1044 | I86: 0.1 | J86: 344.52 | K86: Tamil Nadu | L86: =IF(ISNUMBER(F86),F86,IFERROR(DATE(VALUE(RIGHT(F86,4)),VALUE(LEFT(F86,FIND("/",F86)-1)),VALUE(MID(F86,FIND("/",F86)+1,FIND("/",F86,FIND("/",F86)+1)-FIND("/",F86)-1))),"")) -> 43417 | M86: =YEAR(L86) -> 2018 | N86: =MONTH(L86) -> 11 | O86: =TEXT(L86,"yyyy-mm") -> 2018-11
A87: OD86 | B87: Willams | C87: Oil & Masala | D87: Spices | E87: Dindigul | F87: 5/28/2018 | G87: South | H87: 2129 | I87: 0.25 | J87: 659.99 | K87: Tamil Nadu | L87: =IF(ISNUMBER(F87),F87,IFERROR(DATE(VALUE(RIGHT(F87,4)),VALUE(LEFT(F87,FIND("/",F87)-1)),VALUE(MID(F87,FIND("/",F87)+1,FIND("/",F87,FIND("/",F87)+1)-FIND("/",F87)-1))),"")) -> 43248 | M87: =YEAR(L87) -> 2018 | N87: =MONTH(L87) -> 5 | O87: =TEXT(L87,"yyyy-mm") -> 2018-05
A88: OD87 | B88: Sharon | C88: Food Grains | D88: Rice | E88: Theni | F88: 10/26/2018 | G88: Central | H88: 1759 | I88: 0.1 | J88: 615.65 | K88: Tamil Nadu | L88: =IF(ISNUMBER(F88),F88,IFERROR(DATE(VALUE(RIGHT(F88,4)),VALUE(LEFT(F88,FIND("/",F88)-1)),VALUE(MID(F88,FIND("/",F88)+1,FIND("/",F88,FIND("/",F88)+1)-FIND("/",F88)-1))),"")) -> 43399 | M88: =YEAR(L88) -> 2018 | N88: =MONTH(L88) -> 10 | O88: =TEXT(L88,"yyyy-mm") -> 2018-10
A89: OD88 | B89: Ramesh | C89: Eggs, Meat & Fish | D89: Eggs | E89: Viluppuram | F89: 10/26/2018 | G89: Central | H89: 1663 | I89: 0.26 | J89: 665.2 | K89: Tamil Nadu | L89: =IF(ISNUMBER(F89),F89,IFERROR(DATE(VALUE(RIGHT(F89,4)),VALUE(LEFT(F89,FIND("/",F89)-1)),VALUE(MID(F89,FIND("/",F89)+1,FIND("/",F89,FIND("/",F89)+1)-FIND("/",F89)-1))),"")) -> 43399 | M89: =YEAR(L89) -> 2018 | N89: =MONTH(L89) -> 10 | O89: =TEXT(L89,"yyyy-mm") -> 2018-10
A90: OD89 | B90: Sheeba | C90: Bakery | D90: Breads & Buns | E90: Perambalur | F90: 42859 | G90: Central | H90: 2111 | I90: 0.21 | J90: 189.99 | K90: Tamil Nadu | L90: =IF(ISNUMBER(F90),F90,IFERROR(DATE(VALUE(RIGHT(F90,4)),VALUE(LEFT(F90,FIND("/",F90)-1)),VALUE(MID(F90,FIND("/",F90)+1,FIND("/",F90,FIND("/",F90)+1)-FIND("/",F90)-1))),"")) -> 42859 | M90: =YEAR(L90) -> 2017 | N90: =MONTH(L90) -> 5 | O90: =TEXT(L90,"yyyy-mm") -> 2017-05
A91: OD90 | B91: Krithika | C91: Food Grains | D91: Dals & Pulses | E91: Madurai | F91: 9/17/2017 | G91: West | H91: 1878 | I91: 0.12 | J91: 450.72 | K91: Tamil Nadu | L91: =IF(ISNUMBER(F91),F91,IFERROR(DATE(VALUE(RIGHT(F91,4)),VALUE(LEFT(F91,FIND("/",F91)-1)),VALUE(MID(F91,FIND("/",F91)+1,FIND("/",F91,FIND("/",F91)+1)-FIND("/",F91)-1))),"")) -> 42995 | M91: =YEAR(L91) -> 2017 | N91: =MONTH(L91) -> 9 | O91: =TEXT(L91,"yyyy-mm") -> 2017-09
A92: OD91 | B92: Willams | C92: Eggs, Meat & Fish | D92: Chicken | E92: Ooty | F92: 9/17/2017 | G92: West | H92: 769 | I92: 0.34 | J92: 46.14 | K92: Tamil Nadu | L92: =IF(ISNUMBER(F92),F92,IFERROR(DATE(VALUE(RIGHT(F92,4)),VALUE(LEFT(F92,FIND("/",F92)-1)),VALUE(MID(F92,FIND("/",F92)+1,FIND("/",F92,FIND("/",F92)+1)-FIND("/",F92)-1))),"")) -> 42995 | M92: =YEAR(L92) -> 2017 | N92: =MONTH(L92) -> 9 | O92: =TEXT(L92,"yyyy-mm") -> 2017-09
A93: OD92 | B93: Roshan | C93: Beverages | D93: Health Drinks | E93: Virudhunagar | F93: 9/17/2017 | G93: West | H93: 1241 | I93: 0.14 | J93: 409.53 | K93: Tamil Nadu | L93: =IF(ISNUMBER(F93),F93,IFERROR(DATE(VALUE(RIGHT(F93,4)),VALUE(LEFT(F93,FIND("/",F93)-1)),VALUE(MID(F93,FIND("/",F93)+1,FIND("/",F93,FIND("/",F93)+1)-FIND("/",F93)-1))),"")) -> 42995 | M93: =YEAR(L93) -> 2017 | N93: =MONTH(L93) -> 9 | O93: =TEXT(L93,"yyyy-mm") -> 2017-09
A94: OD93 | B94: Ravi | C94: Food Grains | D94: Atta & Flour | E94: Madurai | F94: 1/31/2016 | G94: Central | H94: 2128 | I94: 0.14 | J94: 383.04 | K94: Tamil Nadu | L94: =IF(ISNUMBER(F94),F94,IFERROR(DATE(VALUE(RIGHT(F94,4)),VALUE(LEFT(F94,FIND("/",F94)-1)),VALUE(MID(F94,FIND("/",F94)+1,FIND("/",F94,FIND("/",F94)+1)-FIND("/",F94)-1))),"")) -> 42400 | M94: =YEAR(L94) -> 2016 | N94: =MONTH(L94) -> 1 | O94: =TEXT(L94,"yyyy-mm") -> 2016-01
A95: OD94 | B95: Ram | C95: Fruits & Veggies | D95: Fresh Fruits | E95: Namakkal | F95: 1/31/2016 | G95: Central | H95: 2257 | I95: 0.33 | J95: 270.84 | K95: Tamil Nadu | L95: =IF(ISNUMBER(F95),F95,IFERROR(DATE(VALUE(RIGHT(F95,4)),VALUE(LEFT(F95,FIND("/",F95)-1)),VALUE(MID(F95,FIND("/",F95)+1,FIND("/",F95,FIND("/",F95)+1)-FIND("/",F95)-1))),"")) -> 42400 | M95: =YEAR(L95) -> 2016 | N95: =MONTH(L95) -> 1 | O95: =TEXT(L95,"yyyy-mm") -> 2016-01
A96: OD95 | B96: Mathew | C96: Snacks | D96: Chocolates | E96: Bodi | F96: 1/31/2016 | G96: Central | H96: 1285 | I96: 0.28 | J96: 218.45 | K96: Tamil Nadu | L96: =IF(ISNUMBER(F96),F96,IFERROR(DATE(VALUE(RIGHT(F96,4)),VALUE(LEFT(F96,FIND("/",F96)-1)),VALUE(MID(F96,FIND("/",F96)+1,FIND("/",F96,FIND("/",F96)+1)-FIND("/",F96)-1))),"")) -> 42400 | M96: =YEAR(L96) -> 2016 | N96: =MONTH(L96) -> 1 | O96: =TEXT(L96,"yyyy-mm") -> 2016-01
A97: OD96 | B97: Veena | C97: Eggs, Meat & Fish | D97: Fish | E97: Virudhunagar | F97: 43262 | G97: West | H97: 1230 | I97: 0.13 | J97: 442.8 | K97: Tamil Nadu | L97: =IF(ISNUMBER(F97),F97,IFERROR(DATE(VALUE(RIGHT(F97,4)),VALUE(LEFT(F97,FIND("/",F97)-1)),VALUE(MID(F97,FIND("/",F97)+1,FIND("/",F97,FIND("/",F97)+1)-FIND("/",F97)-1))),"")) -> 43262 | M97: =YEAR(L97) -> 2018 | N97: =MONTH(L97) -> 6 | O97: =TEXT(L97,"yyyy-mm") -> 2018-06
A98: OD97 | B98: Sudha | C98: Food Grains | D98: Atta & Flour | E98: Ooty | F98: 43354 | G98: East | H98: 1856 | I98: 0.21 | J98: 723.84 | K98: Tamil Nadu | L98: =IF(ISNUMBER(F98),F98,IFERROR(DATE(VALUE(RIGHT(F98,4)),VALUE(LEFT(F98,FIND("/",F98)-1)),VALUE(MID(F98,FIND("/",F98)+1,FIND("/",F98,FIND("/",F98)+1)-FIND("/",F98)-1))),"")) -> 43354 | M98: =YEAR(L98) -> 2018 | N98: =MONTH(L98) -> 9 | O98: =TEXT(L98,"yyyy-mm") -> 2018-09
A99: OD98 | B99: Sharon | C99: Fruits & Veggies | D99: Fresh Fruits | E99: Trichy | F99: 6/17/2018 | G99: West | H99: 545 | I99: 0.31 | J99: 125.35 | K99: Tamil Nadu | L99: =IF(ISNUMBER(F99),F99,IFERROR(DATE(VALUE(RIGHT(F99,4)),VALUE(LEFT(F99,FIND("/",F99)-1)),VALUE(MID(F99,FIND("/",F99)+1,FIND("/",F99,FIND("/",F99)+1)-FIND("/",F99)-1))),"")) -> 43268 | M99: =YEAR(L99) -> 2018 | N99: =MONTH(L99) -> 6 | O99: =TEXT(L99,"yyyy-mm") -> 2018-06
A100: OD99 | B100: Vince | C100: Snacks | D100: Chocolates | E100: Dharmapuri | F100: 42895 | G100: Central | H100: 2301 | I100: 0.28 | J100: 391.17 | K100: Tamil Nadu | L100: =IF(ISNUMBER(F100),F100,IFERROR(DATE(VALUE(RIGHT(F100,4)),VALUE(LEFT(F100,FIND("/",F100)-1)),VALUE(MID(F100,FIND("/",F100)+1,FIND("/",F100,FIND("/",F100)+1)-FIND("/",F100)-1))),"")) -> 42895 | M100: =YEAR(L100) -> 2017 | N100: =MONTH(L100) -> 6 | O100: =TEXT(L100,"yyyy-mm") -> 2017-06
...

Sheet Calculations
A1: Metric | B1: Total Sales | C1: Total Profit | D1: Total Orders | E1: Average Discount | F1: Average Order Value | G1: Profit Margin
A2: Value | B2: =SUM(SupermartData[Sales]) -> 14956982 | C2: =SUM(SupermartData[Profit]) -> 3747121.2 | D2: =COUNTA(SupermartData[Order ID]) -> 9994 | E2: =AVERAGE(SupermartData[Discount]) -> 0.22681709 | F2: =B2/D2 -> 1496.5962 | G2: =C2/B2 -> 0.25052656

Sheet Pivot_Overall
A3: Row Labels | B3: Sales Values | C3: Profit Values | E3: Row Labels | F3: Sum of Profit | H3: Row Labels | I3: Sales Values | J3: Sum of Profit | K3: Row Labels | L3: Sum of Sales | M3: Sum of Profit
A4: Bakery | B4: 2112281 | C4: 528521.06 | E4: 0.1 | F4: 132451.16 | H4: 2015-01 | I4: 203014 | J4: 54689.18 | K4: Central | L4: 3468156 | M4: 856806.84
A5: Beverages | B5: 2085313 | C5: 525605.76 | E5: 0.11 | F5: 141644.47 | H5: 2015-02 | I5: 120444 | J5: 32737.87 | K5: East | L5: 4248368 | M5: 1074345.6
A6: Eggs, Meat & Fish | B6: 2267401 | C6: 567357.22 | E6: 0.12 | F6: 136104.25 | H6: 2015-03 | I6: 260072 | J6: 66217.5 | K6: North | L6: 1254 | M6: 401.28
A7: Food Grains | B7: 2115272 | C7: 529162.64 | E7: 0.13 | F7: 135511.87 | H7: 2015-04 | I7: 176187 | J7: 46030.2 | K7: South | L7: 2440461 | M7: 623562.89
A8: Fruits & Veggies | B8: 2100727 | C8: 530400.38 | E8: 0.14 | F8: 142611.11 | H8: 2015-05 | I8: 218740 | J8: 50899.84 | K8: West | L8: 4798743 | M8: 1192004.6
A9: Oil & Masala | B9: 2038442 | C9: 497895.29 | E9: 0.15 | F9: 138646.69 | H9: 2015-06 | I9: 209191 | J9: 51276.99 | K9: Grand Total | L9: 14956982 | M9: 3747121.2
A10: Snacks | B10: 2237546 | C10: 568178.85 | E10: 0.16 | F10: 147889.02 | H10: 2015-07 | I10: 229055 | J10: 56202.42
A11: Grand Total | B11: 14956982 | C11: 3747121.2 | E11: 0.17 | F11: 127199.25 | H11: 2015-08 | I11: 211451 | J11: 48499.68 | K11: Row Labels | L11: Sales Values | M11: Profit Values
E12: 0.18 | F12: 141907.32 | H12: 2015-09 | I12: 356192 | J12: 89985.8 | K12: Bodi | L12: 667177 | M12: 173655.13
A13: Row Labels | B13: Sales Values | C13: Profit Values | E13: 0.19 | F13: 154141.1 | H13: 2015-10 | I13: 226102 | J13: 59400.29 | K13: Chennai | L13: 634963 | M13: 160921.33
A14: Atta & Flour | B14: 534649 | C14: 127861.1 | E14: 0.2 | F14: 128383.84 | H14: 2015-11 | I14: 396619 | J14: 100548.5 | K14: Coimbatore | L14: 634748 | M14: 157399.41
A15: Biscuits | B15: 684083 | C15: 169357.62 | E15: 0.21 | F15: 150594.64 | H15: 2015-12 | I15: 368532 | J15: 96040.84 | K15: Cumbum | L15: 626047 | M15: 156355.13
A16: Breads & Buns | B16: 742586 | C16: 190764.98 | E16: 0.22 | F16: 143161.29 | H16: 2016-01 | I16: 136079 | J16: 34499.19 | K16: Dharmapuri | L16: 571553 | M16: 141593.05
A17: Cakes | B17: 685612 | C17: 168398.46 | E17: 0.23 | F17: 152066.54 | H17: 2016-02 | I17: 148752 | J17: 39076.83 | K17: Dindigul | L17: 575631 | M17: 144872.95
A18: Chicken | B18: 520497 | C18: 124049.89 | E18: 0.24 | F18: 141063.32 | H18: 2016-03 | I18: 242347 | J18: 67550.67 | K18: Kanyakumari | L18: 706764 | M18: 172217.74
A19: Chocolates | B19: 733898 | C19: 183849.34 | E19: 0.25 | F19: 164579.47 | H19: 2016-04 | I19: 231694 | J19: 58075.07 | K19: Karur | L19: 642273 | M19: 169305.94
A20: Cookies | B20: 768213 | C20: 190643.7 | E20: 0.26 | F20: 156712.48 | H20: 2016-05 | I20: 276958 | J20: 70837.51 | K20: Krishnagiri | L20: 637273 | M20: 160477.48
A21: Dals & Pulses | B21: 523371 | C21: 130232.29 | E21: 0.27 | F21: 162074.09 | H21: 2016-06 | I21: 216643 | J21: 59144.86 | K21: Madurai | L21: 617836 | M21: 152548.61
A22: Edible Oil & Ghee | B22: 668086 | C22: 168593.58 | E22: 0.28 | F22: 141868.29 | H22: 2016-07 | I22: 194498 | J22: 49658.57 | K22: Nagercoil | L22: 551435 | M22: 137848.47
A23: Eggs | B23: 575156 | C23: 144669.92 | E23: 0.29 | F23: 142627.31 | H23: 2016-08 | I23: 266132 | J23: 67908.79 | K23: Namakkal | L23: 598530 | M23: 145502.1
A24: Fish | B24: 560548 | C24: 147248.01 | E24: 0.3 | F24: 135537.47 | H24: 2016-09 | I24: 405161 | J24: 105353.67 | K24: Ooty | L24: 599292 | M24: 150078.92
A25: Fresh Fruits | B25: 551212 | C25: 134668.35 | E25: 0.31 | F25: 139034.3 | H25: 2016-10 | I25: 228997 | J25: 55334.88 | K25: Perambalur | L25: 659738 | M25: 171132.19
... A29: Mutton | B29: 611200 | C29: 151389.4 | E29: 0.35 | F29: 150480.87 | H29: 2017-02 | I29: 203846 | J29: 50758.77 | K29: Tenkasi | L29: 643652 | M29: 156230.72
A30: Noodles | B30: 735435 | C30: 193685.81 | E30: Grand Total | F30: 3747121.2 | H30: 2017-03 | I30: 288295 | J30: 73797.38 | K30: Theni | L30: 579553 | M30: 142739.78
A31: Organic Fruits | B31: 503402 | C31: 130862.33 | H31: 2017-04 | I31: 280724 | J31: 65592.93 | K31: Tirunelveli | L31: 659812 | M31: 165169.01
A32: Organic Staples | B32: 558929 | C32: 144136.89 | H32: 2017-05 | I32: 388739 | J32: 99154.68 | K32: Trichy | L32: 541403 | M32: 136059.94
A33: Organic Vegetables | B33: 520271 | C33: 133596.37 | H33: 2017-06 | I33: 267878 | J33: 62796.59 | K33: Vellore | L33: 676550 | M33: 174073.01
A34: Rice | B34: 498323 | C34: 126932.36 | H34: 2017-07 | I34: 317912 | J34: 78502.65 | K34: Viluppuram | L34: 581274 | M34: 144200.64
A35: Soft Drinks | B35: 1033874 | C35: 258135.97 | H35: 2017-08 | I35: 349149 | J35: 89800.06 | K35: Virudhunagar | L35: 606820 | M35: 150816.69
A36: Spices | B36: 672876 | C36: 160302.6 | H36: 2017-09 | I36: 355404 | J36: 85347.05 | K36: Grand Total | L36: 14956982 | M36: 3747121.2
A37: Grand Total | B37: 14956982 | C37: 3747121.2 | H37: 2017-10 | I37: 368989 | J37: 84244.3
H38: 2017-11 | I38: 427532 | J38: 105582.16
H39: 2017-12 | I39: 397594 | J39: 103007.48
H40: 2018-01 | I40: 337185 | J40: 82424.57
H41: 2018-02 | I41: 357259 | J41: 90832.7
H42: 2018-03 | I42: 456482 | J42: 111969.15
H43: 2018-04 | I43: 339747 | J43: 84652.87
H44: 2018-05 | I44: 366890 | J44: 89521.41
H45: 2018-06 | I45: 334982 | J45: 84524.15
H46: 2018-07 | I46: 366018 | J46: 92166.8
H47: 2018-08 | I47: 393698 | J47: 95920.86
H48: 2018-09 | I48: 589384 | J48: 152937.96
H49: 2018-10 | I49: 413301 | J49: 107752.58
... H52: Grand Total | I52: 14956982 | J52: 3747121.2

Sheet Dashboard
A1: SUPERMART GROCERY SALES DASHBOARD
A3: TOTAL SALES | E3: TOTAL PROFIT | I3: TOTAL ORDERS | M3: AVERAGE DISCOUNT | Q3: AVERAGE ORDER VALUE | U3: PROFIT MARGIN
A5: =Calculations!B2 -> 14956982 | E5: =Calculations!C2 -> 3747121.2 | I5: =Calculations!D2 -> 9994 | M5: =Calculations!E2 -> 0.22681709 | Q5: =Calculations!F2 -> 1496.5962 | U5: =Calculations!G2 -> 0.25052656
